gravitas.cp311-win_amd64.pyd
gravitas-0.2.12.dist-info/METADATA
gravitas-0.2.12.dist-info/WHEEL
gravitas-0.2.12.dist-info/top_level.txt
gravitas-0.2.12.dist-info/RECORD
