Metadata-Version: 2.4
Name: gravitas
Version: 0.2.12
Summary: Gravity field modeling for astrodynamics
Author-email: Liam Robinson <liamers127@gmail.com>
Project-URL: Repository, https://github.com/liamrobinson1/gravitas
Requires-Python: >=3.10
